rustcsv/test_benchmark.py
rustcsv/_version.py
rustcsv/test_rustcsv.py
rustcsv/__main__.py
rustcsv/_rustcsv.cpython-36m-x86_64-linux-gnu.so
rustcsv/__init__.py
rustcsv/error.py
rustcsv-0.1.0a16.dist-info/top_level.txt
rustcsv-0.1.0a16.dist-info/RECORD
rustcsv-0.1.0a16.dist-info/METADATA
rustcsv-0.1.0a16.dist-info/entry_points.txt
rustcsv-0.1.0a16.dist-info/WHEEL
