Metadata-Version: 2.1
Name: rustcsv
Version: 0.1.0a16
Summary: UNKNOWN
Home-page: https://github.com/joar/rust-csv-py
Author: Joar Wandborg
Author-email: joar@wandborg.se
License: UNKNOWN
Platform: UNKNOWN
Classifier: License :: OSI Approved :: MIT License
Classifier: Development Status :: 3 - Alpha
Classifier: Intended Audience :: Developers
Classifier: Programming Language :: Python
Classifier: Programming Language :: Rust
Classifier: Operating System :: POSIX
Classifier: Operating System :: MacOS :: MacOS X
Requires-Dist: attrs (>=18.2.0)
Requires-Dist: click (>=6.7)
